AUTHORS
ChangeLog
LICENSE
MANIFEST.in
README.rst
setup.py
docs/Makefile
docs/source/conf.py
docs/source/index.rst
docs/source/services/capitolwords.rst
docs/source/services/congress.rst
docs/source/services/congress_deprecated.rst
docs/source/services/openstates.rst
docs/source/sunlight/cache.rst
docs/source/sunlight/config.rst
docs/source/sunlight/errors.rst
docs/source/sunlight/pagination.rst
docs/source/sunlight/service.rst
examples/paging
examples/capitolwords/gingrich_words
examples/capitolwords/internet_dates
examples/capitolwords/july_2010_phrases
examples/capitolwords/legislators_who_love_free_market
examples/capitolwords/obama_records
examples/congress/who_is_my_rep
examples/congress_deprecated/get_nacy
examples/cross-api/death-metal
examples/cross-api/free_market_lovers
examples/openstates/ca_bill_lookup
examples/openstates/ca_dems
examples/openstates/get_json_vt_agro
examples/openstates/get_rep_by_lat_lon
examples/openstates/md_ctty_lookup
examples/openstates/md_cttys
examples/openstates/tx_events
examples/openstates/vt_agro_bills
sunlight/__init__.py
sunlight/cache.py
sunlight/cli.py
sunlight/config.py
sunlight/errors.py
sunlight/pagination.py
sunlight/service.py
sunlight.egg-info/PKG-INFO
sunlight.egg-info/SOURCES.txt
sunlight.egg-info/dependency_links.txt
sunlight.egg-info/entry_points.txt
sunlight.egg-info/requires.txt
sunlight.egg-info/top_level.txt
sunlight/services/__init__.py
sunlight/services/capitolwords.py
sunlight/services/congress.py
sunlight/services/congress_deprecated.py
sunlight/services/opencivic.py
sunlight/services/openstates.py