Metadata-Version: 1.0
Name: sunlight
Version: 1.2.8
Summary: Unified Sunlight API bindings
Home-page: https://github.com/sunlightlabs/python-sunlight
Author: Paul Tagliamonte
Author-email: paultag@sunlightfoundation.com
License: BSD
Platform: any
